{
 "aggregate_function_based_on": "base_net_total",
 "based_on": "",
 "chart_name": "Today's Sale (Store Wise) -APF",
 "chart_type": "Group By",
 "creation": "2022-01-12 12:45:33.376210",
 "docstatus": 0,
 "doctype": "Dashboard Chart",
 "document_type": "Sales Invoice",
 "dynamic_filters_json": "[]",
 "filters_json": "[[\"Sales Invoice\",\"company\",\"=\",\"ABU DHABI POULTRY FARM - SOLE PROPRIETORSHIP L.L.C.\",false],[\"Sales Invoice\",\"status\",\"not in\",[\"Return\",\"Cancelled\",\"Draft\",null],false],[\"Sales Invoice\",\"docstatus\",\"=\",\"1\",false],[\"Sales Invoice\",\"posting_date\",\"Timespan\",\"today\",false]]",
 "group_by_based_on": "cost_center",
 "group_by_type": "Sum",
 "idx": 0,
 "is_public": 0,
 "is_standard": 1,
 "last_synced_on": "2022-02-01 16:53:18.664368",
 "modified": "2022-02-01 16:56:54.795104",
 "modified_by": "Administrator",
 "module": "Selling",
 "name": "Today's Sale (Store Wise) -APF",
 "number_of_groups": 0,
 "owner": "Administrator",
 "source": "",
 "time_interval": "Yearly",
 "timeseries": 0,
 "timespan": "Last Year",
 "type": "Bar",
 "use_report_chart": 0,
 "value_based_on": "",
 "y_axis": []
}